extend_ai_toolkit/__init__.py
extend_ai_toolkit/__version__.py
extend_ai_toolkit/crewai/__init__.py
extend_ai_toolkit/crewai/extend_tool.py
extend_ai_toolkit/crewai/toolkit.py
extend_ai_toolkit/examples/crewai-agent.py
extend_ai_toolkit/examples/langchain-react-agent.py
extend_ai_toolkit/examples/openai-agent.py
extend_ai_toolkit/langchain/__init__.py
extend_ai_toolkit/langchain/extend_tool.py
extend_ai_toolkit/langchain/toolkit.py
extend_ai_toolkit/modelcontextprotocol/__init__.py
extend_ai_toolkit/modelcontextprotocol/main.py
extend_ai_toolkit/modelcontextprotocol/main_sse.py
extend_ai_toolkit/modelcontextprotocol/options.py
extend_ai_toolkit/modelcontextprotocol/server.py
extend_ai_toolkit/modelcontextprotocol/client/__init__.py
extend_ai_toolkit/modelcontextprotocol/client/anthropic_chat_client.py
extend_ai_toolkit/modelcontextprotocol/client/chat_client.py
extend_ai_toolkit/modelcontextprotocol/client/mcp_client.py
extend_ai_toolkit/modelcontextprotocol/client/openai_chat_client.py
extend_ai_toolkit/notebooks/langchain-react-agent.ipynb
extend_ai_toolkit/openai/__init__.py
extend_ai_toolkit/openai/extend_tool.py
extend_ai_toolkit/openai/toolkit.py
extend_ai_toolkit/shared/__init__.py
extend_ai_toolkit/shared/agent_toolkit.py
extend_ai_toolkit/shared/api.py
extend_ai_toolkit/shared/auth.py
extend_ai_toolkit/shared/configuration.py
extend_ai_toolkit/shared/enums.py
extend_ai_toolkit/shared/functions.py
extend_ai_toolkit/shared/helpers.py
extend_ai_toolkit/shared/interfaces.py
extend_ai_toolkit/shared/models.py
extend_ai_toolkit/shared/prompts.py
extend_ai_toolkit/shared/schemas.py
extend_ai_toolkit/shared/tools.py
extend_ai_toolkit/shared/utils.py
extend_ai_toolkit-1.3.0.dist-info/METADATA
extend_ai_toolkit-1.3.0.dist-info/WHEEL
extend_ai_toolkit-1.3.0.dist-info/licenses/LICENSE
extend_ai_toolkit-1.3.0.dist-info/licenses/LICENSE.bak
extend_ai_toolkit-1.3.0.dist-info/RECORD
