Metadata-Version: 2.4
Name: extend_ai_toolkit
Version: 1.3.0
Summary: Extend AI Toolkit
Project-URL: Issue Tracker, https://github.com/paywithextend/extend-ai-toolkit/issues
Project-URL: Source Code, https://github.com/paywithextend/extend-ai-toolkit
Author-email: Extend Engineering <support@paywithextend.com>
License: MIT
License-File: LICENSE
License-File: LICENSE.bak
Keywords: agent,ai,api,extend,mcp,payments,virtual cards
Requires-Python: >=3.10
Requires-Dist: build
Requires-Dist: colorama>=0.4.4
Requires-Dist: langchain==0.3.20
Requires-Dist: mcp>=1.4.1
Requires-Dist: mypy==1.15.0
Requires-Dist: openai-agents==0.0.4
Requires-Dist: openai<2.0.0,>=1.66.3
Requires-Dist: paywithextend==2.0.0
Requires-Dist: pydantic>=1.10.2
Requires-Dist: python-dotenv>=1.0.1
Requires-Dist: requests==2.32.3
Requires-Dist: starlette<0.46.0,>=0.40.0
Provides-Extra: dev
Requires-Dist: crewai>=0.108.0; extra == 'dev'
Requires-Dist: mypy>=1.11.1; extra == 'dev'
Requires-Dist: pytest-asyncio>=0.26.0; extra == 'dev'
Requires-Dist: pytest>=7.0.1; extra == 'dev'
Requires-Dist: ruff>=0.6.1; extra == 'dev'
